vorteex/__init__.py
vorteex/__main__.py
vorteex/api.py
vorteex/config.py
vorteex/output.py
vorteex/prompt.py
vorteex/settings.py
vorteex/utils.py
vorteex/commands/__init__.py
vorteex/commands/auth.py
vorteex/commands/configure.py
vorteex/commands/query.py
vorteex-0.0.1.data/scripts/vorteex
vorteex-0.0.1.dist-info/LICENSE
vorteex-0.0.1.dist-info/METADATA
vorteex-0.0.1.dist-info/WHEEL
vorteex-0.0.1.dist-info/top_level.txt
vorteex-0.0.1.dist-info/RECORD
