Metadata-Version: 2.1
Name: vorteex
Version: 0.0.1
Summary: Python library and CLI tool for Vorteex (https://vorteex.io)
Home-page: https://github.com/SYBERFY/vorteex-cli
Author: Adrian
Author-email: adrian@syberfy.com
License: gpl-3.0
Platform: UNKNOWN
Classifier: Development Status :: 3 - Alpha
Classifier: Programming Language :: Python :: 3.7
Classifier: Programming Language :: Python :: 3.8
Classifier: Programming Language :: Python :: 3.9
Classifier: Topic :: Security
Classifier: Natural Language :: English
Classifier: Operating System :: OS Independent
Classifier: License :: OSI Approved :: GNU General Public License v3 (GPLv3)
Requires-Python: >=3.7
Requires-Dist: pyinquirer
Requires-Dist: requests
Requires-Dist: validators
